jengaapi/__init__.py
jengaapi/configs/__init__.py
jengaapi/configs/config.py
jengaapi/services/__init__.py
jengaapi/services/account_services.py
jengaapi/services/authorization_service.py
jengaapi/services/miscellaneous_services.py
jengaapi/services/mpgs_direct_integration_service.py
jengaapi/services/receive_money_queries_services.py
jengaapi/services/receive_money_services.py
jengaapi/services/send_money_imt_services.py
jengaapi/services/send_money_services.py
jengaapi/services/utils.py
python_jengaapi-2.0.1.dist-info/LICENSE
python_jengaapi-2.0.1.dist-info/METADATA
python_jengaapi-2.0.1.dist-info/WHEEL
python_jengaapi-2.0.1.dist-info/top_level.txt
python_jengaapi-2.0.1.dist-info/RECORD
