Metadata-Version: 2.1
Name: python-jengaapi
Version: 2.0.1
Summary: A python wrapper for the Jenga API.
Home-page: https://github.com/MainaKamau92/JengaAPIPythonWrapper
Author: Maina Kamau
Author-email: lewiikamaa8@gmail.com
License: BSD-2-Clause
Classifier: Intended Audience :: Developers
Classifier: License :: OSI Approved :: BSD License
Classifier: Operating System :: OS Independent
Classifier: Programming Language :: Python
Classifier: Programming Language :: Python :: 3
Classifier: Programming Language :: Python :: 3 :: Only
Classifier: Programming Language :: Python :: 3.6
Classifier: Programming Language :: Python :: 3.7
Classifier: Programming Language :: Python :: 3.8
Classifier: Topic :: Internet :: WWW/HTTP
Classifier: Topic :: Internet :: WWW/HTTP :: Dynamic Content
Requires-Python: >=3.6
License-File: LICENSE
Requires-Dist: requests (>=2.5.4.1)
Requires-Dist: pycryptodome (==3.10.1)
